luziip/__init__.py
luziip/luziip.py
luziip-0.3.dist-info/METADATA
luziip-0.3.dist-info/WHEEL
luziip-0.3.dist-info/top_level.txt
luziip-0.3.dist-info/RECORD
