Metadata-Version: 2.2
Name: luziip
Version: 0.3
Summary: A simple IP info fetcher
Home-page: https://luzitool.ct.ws/luziip.php
Author: luzi inc
Author-email: help@luzitool.ct.ws
Classifier: Programming Language :: Python :: 3
Classifier: License :: OSI Approved :: MIT License
Classifier: Operating System :: OS Independent
Requires-Python: >=3.6
Requires-Dist: requests
Dynamic: author
Dynamic: author-email
Dynamic: classifier
Dynamic: description
Dynamic: description-content-type
Dynamic: home-page
Dynamic: requires-dist
Dynamic: requires-python
Dynamic: summary
